py_dev_support/__init__.py
py_dev_support/commit_all.py
py_dev_support/release.py
py_dev_support/version.py
py_dev_support-0.1.16.dist-info/entry_points.txt
py_dev_support-0.1.16.dist-info/LICENSE
py_dev_support-0.1.16.dist-info/WHEEL
py_dev_support-0.1.16.dist-info/METADATA
py_dev_support-0.1.16.dist-info/RECORD
