Metadata-Version: 2.1
Name: py_dev_support
Version: 0.1.16
Summary: This module provide some cli tool for dev.
Classifier: License :: OSI Approved :: MIT License
Requires-Dist: click ==8.1.3
Requires-Dist: toml ==0.10.2
